cognite_ml-0.0.1.dist-info/METADATA
cognite_ml-0.0.1.dist-info/RECORD
cognite_ml-0.0.1.dist-info/WHEEL
cognite_ml-0.0.1.dist-info/top_level.txt
ml_dev/__init__.py
test/__init__.py
