Metadata-Version: 2.1
Name: cognite-ml
Version: 0.0.1
Summary: Cognite Machine Learning Toolkit
Home-page: https://github.com/cognitedata/ml_dev
Author: Data Science Cognite
Author-email: que.tran@cognite.com
License: UNKNOWN
Download-URL: https://github.com/cognitedata/ml_dev/archive/0.0.1.tar.gz
Platform: UNKNOWN
